<xml xmlns="http://www.w3.org/1999/xhtml">
  <tab name="Init" type="InitTab" active="false" scrollx="20" scrolly="20" scale="0.9"></tab>
  <tab name="New Tab" type="CommonTab" active="true" scrollx="186.95165273518194" scrolly="-60.93208020513066" scale="0.44577591779121417">
    <block xmlns="https://developers.google.com/blockly/xml" type="eventHTMLElem" id="0:2Ga/V$yHt]9/o#zNu]" x="110" y="930">
      <field name="EVENT">click</field>
      <field name="PARENT">FALSE</field>
      <value name="ID">
        <shadow type="text" id="6mwv;jLzZ04nW^%7o9!]">
          <field name="TEXT">Black</field>
        </shadow>
      </value>
      <statement name="DO">
        <block type="setMaterialColor" id="xRGrFrlCL*7m*ys^f6-y">
          <mutation xmlns="http://www.w3.org/1999/xhtml" flexcolinput="false" usecsscolor="false"></mutation>
          <field name="MAT_COL_NAME">Color_1</field>
          <value name="MATERIAL">
            <shadow type="materialList" id="*?QB|#8b!1B9Ei;MM4Q%">
              <field name="FIELDNAME">carpaint</field>
            </shadow>
          </value>
          <value name="R">
            <shadow type="math_number" id="u/#rnz;lj)ZD3tQ9|PE5">
              <field name="NUM">0</field>
            </shadow>
          </value>
          <value name="G">
            <shadow type="math_number" id="(0%H}FK`2;[]yY?P65%%">
              <field name="NUM">0</field>
            </shadow>
          </value>
          <value name="B">
            <shadow type="math_number" id="TOdHOLW(Pe476%AGU/,L">
              <field name="NUM">0</field>
            </shadow>
          </value>
          <next>
            <block type="setMaterialColor" id="!Z:o:qXGRA;37)8j_HDg">
              <mutation xmlns="http://www.w3.org/1999/xhtml" flexcolinput="false" usecsscolor="false"></mutation>
              <field name="MAT_COL_NAME">Color_2</field>
              <value name="MATERIAL">
                <shadow type="materialList" id="-GjAw`gz_t/ZFrMw`Ef@">
                  <field name="FIELDNAME">carpaint</field>
                </shadow>
              </value>
              <value name="R">
                <shadow type="math_number" id="C[|J)`1.:];+C@Rb2NF~">
                  <field name="NUM">0</field>
                </shadow>
              </value>
              <value name="G">
                <shadow type="math_number" id="FRML:H0xfg#0ll5]d!0`">
                  <field name="NUM">0</field>
                </shadow>
              </value>
              <value name="B">
                <shadow type="math_number" id="=JKjBf.tHEQoC1xnpQU2">
                  <field name="NUM">0</field>
                </shadow>
              </value>
            </block>
          </next>
        </block>
      </statement>
    </block>
    <block xmlns="https://developers.google.com/blockly/xml" type="eventHTMLElem" id="ejyYfZ^gB8Ri0({c$d7*" x="110" y="1110">
      <field name="EVENT">click</field>
      <field name="PARENT">FALSE</field>
      <value name="ID">
        <shadow type="text" id="A8NEEr?trD[bhKn/(uxE">
          <field name="TEXT">BluePurple</field>
        </shadow>
      </value>
      <statement name="DO">
        <block type="setMaterialColor" id="VkSc+wcMwYOlDR~!^YTl">
          <mutation xmlns="http://www.w3.org/1999/xhtml" flexcolinput="false" usecsscolor="false"></mutation>
          <field name="MAT_COL_NAME">Color_1</field>
          <value name="MATERIAL">
            <shadow type="materialList" id="65eQ,^_VW2,yVj3.W{Pg">
              <field name="FIELDNAME">carpaint</field>
            </shadow>
          </value>
          <value name="R">
            <shadow type="math_number" id="#:P+F-H;kR*PH-8#ouT|">
              <field name="NUM">0.167263</field>
            </shadow>
          </value>
          <value name="G">
            <shadow type="math_number" id="`IAYEq,:|-s?V,Il2HOp">
              <field name="NUM">0</field>
            </shadow>
          </value>
          <value name="B">
            <shadow type="math_number" id="8*dIar_bB{=y1Xmoz1n3">
              <field name="NUM">0.881073</field>
            </shadow>
          </value>
          <next>
            <block type="setMaterialColor" id="5P|SH`vH{Wm(3QXEKPS4">
              <mutation xmlns="http://www.w3.org/1999/xhtml" flexcolinput="false" usecsscolor="false"></mutation>
              <field name="MAT_COL_NAME">Color_2</field>
              <value name="MATERIAL">
                <shadow type="materialList" id="/Ew)XiKye3-}Dj|30qWZ">
                  <field name="FIELDNAME">carpaint</field>
                </shadow>
              </value>
              <value name="R">
                <shadow type="math_number" id="r#~^5,WI[d2iIMQu4xb;">
                  <field name="NUM">0.014415</field>
                </shadow>
              </value>
              <value name="G">
                <shadow type="math_number" id="FH[}GT+4:J~D=Y7L;z])">
                  <field name="NUM">0</field>
                </shadow>
              </value>
              <value name="B">
                <shadow type="math_number" id="+$Rp@sDD~0C+%Jcm|`7h">
                  <field name="NUM">1</field>
                </shadow>
              </value>
            </block>
          </next>
        </block>
      </statement>
    </block>
    <block xmlns="https://developers.google.com/blockly/xml" type="eventHTMLElem" id="E!.#wwE0Uv/Mt@fmVW+%" x="110" y="1290">
      <field name="EVENT">click</field>
      <field name="PARENT">FALSE</field>
      <value name="ID">
        <shadow type="text" id="nKhH;(RpUqtVQNJfb[uH">
          <field name="TEXT">RedGold</field>
        </shadow>
      </value>
      <statement name="DO">
        <block type="setMaterialColor" id="}FjDf((YO5J0{m)Qm!|e">
          <mutation xmlns="http://www.w3.org/1999/xhtml" flexcolinput="false" usecsscolor="false"></mutation>
          <field name="MAT_COL_NAME">Color_1</field>
          <value name="MATERIAL">
            <shadow type="materialList" id="o_i87Ui{5o!)J;,%S6!z">
              <field name="FIELDNAME">carpaint</field>
            </shadow>
          </value>
          <value name="R">
            <shadow type="math_number" id="fR/~UM@g1t#iA^R0,GmH">
              <field name="NUM">1</field>
            </shadow>
          </value>
          <value name="G">
            <shadow type="math_number" id=";P$d3L4SPn|8Ho+?5Tb@">
              <field name="NUM">0.362139</field>
            </shadow>
          </value>
          <value name="B">
            <shadow type="math_number" id="VJm2!2xqa@^RXBEP_+Kj">
              <field name="NUM">0</field>
            </shadow>
          </value>
          <next>
            <block type="setMaterialColor" id="O$Tw7=aEoh#Bxn()sxSn">
              <mutation xmlns="http://www.w3.org/1999/xhtml" flexcolinput="false" usecsscolor="false"></mutation>
              <field name="MAT_COL_NAME">Color_2</field>
              <value name="MATERIAL">
                <shadow type="materialList" id="abS8_/X;eq%1$3[)R=Gc">
                  <field name="FIELDNAME">carpaint</field>
                </shadow>
              </value>
              <value name="R">
                <shadow type="math_number" id="[[@J4=PQuccb%9|-}K6T">
                  <field name="NUM">1</field>
                </shadow>
              </value>
              <value name="G">
                <shadow type="math_number" id="AGuit-OC?|:X#Qo.y@U[">
                  <field name="NUM">0</field>
                </shadow>
              </value>
              <value name="B">
                <shadow type="math_number" id="kuB#w]Y=(_@G}SsNLLU@">
                  <field name="NUM">0</field>
                </shadow>
              </value>
            </block>
          </next>
        </block>
      </statement>
    </block>
    <block xmlns="https://developers.google.com/blockly/xml" type="eventHTMLElem" id="Ix/APARE(H;S;pR6bw/(" x="110" y="1450">
      <field name="EVENT">click</field>
      <field name="PARENT">FALSE</field>
      <value name="ID">
        <shadow type="text" id=".xM?_n*9RTVp7PfO+Tv)">
          <field name="TEXT">Red</field>
        </shadow>
      </value>
      <statement name="DO">
        <block type="setMaterialColor" id="s.A%%kHkr{igKtKdr^0G">
          <mutation xmlns="http://www.w3.org/1999/xhtml" flexcolinput="false" usecsscolor="false"></mutation>
          <field name="MAT_COL_NAME">Color_1</field>
          <value name="MATERIAL">
            <shadow type="materialList" id="Gvg01R,)C#IeU^k+DukD">
              <field name="FIELDNAME">carpaint</field>
            </shadow>
          </value>
          <value name="R">
            <shadow type="math_number" id="l#mN7{^U4k~k=_${-.%2">
              <field name="NUM">1</field>
            </shadow>
          </value>
          <value name="G">
            <shadow type="math_number" id="(58xQ|YN)EoJys2S=AVt">
              <field name="NUM">0</field>
            </shadow>
          </value>
          <value name="B">
            <shadow type="math_number" id="mf=;:N)FravR?8#RO?_,">
              <field name="NUM">0</field>
            </shadow>
          </value>
          <next>
            <block type="setMaterialColor" id=":B]naulre(z.pdtOJyMz">
              <mutation xmlns="http://www.w3.org/1999/xhtml" flexcolinput="false" usecsscolor="false"></mutation>
              <field name="MAT_COL_NAME">Color_2</field>
              <value name="MATERIAL">
                <shadow type="materialList" id="Eszk]weL/T^`miOh$:xI">
                  <field name="FIELDNAME">carpaint</field>
                </shadow>
              </value>
              <value name="R">
                <shadow type="math_number" id="!1zE@%)xV7Gr2M-?@Cn3">
                  <field name="NUM">1</field>
                </shadow>
              </value>
              <value name="G">
                <shadow type="math_number" id="=.q[ggoTo5Ah6%2iI{/t">
                  <field name="NUM">0</field>
                </shadow>
              </value>
              <value name="B">
                <shadow type="math_number" id="lI:!Xyd!B[TpRPat@f[6">
                  <field name="NUM">0</field>
                </shadow>
              </value>
            </block>
          </next>
        </block>
      </statement>
    </block>
  </tab>
  <editorsettings viewport-x="903.5999999999999" viewport-y="37" viewport-w="614.4" viewport-h="364.5" viewport-hidden="false" toolbox-library-mode="false" toolbox-minimized-mode="false"></editorsettings>
</xml>